touchtechnology_public-0.0.4-py3.9-nspkg.pth
touchtechnology/public/__init__.py
touchtechnology/public/decorators.py
touchtechnology/public/views.py
touchtechnology/public/db/__init__.py
touchtechnology/public/db/models.py
touchtechnology/public/forms/__init__.py
touchtechnology/public/forms/fields.py
touchtechnology/public/forms/widgets.py
touchtechnology/public/mixins/__init__.py
touchtechnology/public/mixins/cbv.py
touchtechnology/public/mixins/schema.py
touchtechnology/public/static/touchtechnology/public/admin/css/boolean.css
touchtechnology_public-0.0.4.dist-info/METADATA
touchtechnology_public-0.0.4.dist-info/WHEEL
touchtechnology_public-0.0.4.dist-info/namespace_packages.txt
touchtechnology_public-0.0.4.dist-info/top_level.txt
touchtechnology_public-0.0.4.dist-info/RECORD
